jupyter_ai_magics/_version.py
ghn_jupyter_ai_magics-0.0.9.dist-info/METADATA
ghn_jupyter_ai_magics-0.0.9.dist-info/WHEEL
ghn_jupyter_ai_magics-0.0.9.dist-info/entry_points.txt
ghn_jupyter_ai_magics-0.0.9.dist-info/licenses/LICENSE
ghn_jupyter_ai_magics-0.0.9.dist-info/RECORD
